{
  "hash": "7920c456",
  "configHash": "25553259",
  "lockfileHash": "afc8bf9c",
  "browserHash": "f83ccab9",
  "optimized": {
    "react": {
      "src": "../../node_modules/react/index.js",
      "file": "react.js",
      "fileHash": "ac6cfadd",
      "needsInterop": true
    },
    "react-dom/client": {
      "src": "../../node_modules/react-dom/client.js",
      "file": "react-dom_client.js",
      "fileHash": "7b7cbb3b",
      "needsInterop": true
    },
    "react-router-dom": {
      "src": "../../node_modules/react-router-dom/dist/index.mjs",
      "file": "react-router-dom.js",
      "fileHash": "b62d9174",
      "needsInterop": false
    },
    "react-icons/vsc": {
      "src": "../../node_modules/react-icons/vsc/index.mjs",
      "file": "react-icons_vsc.js",
      "fileHash": "975a730c",
      "needsInterop": false
    },
    "framer-motion": {
      "src": "../../node_modules/framer-motion/dist/es/index.mjs",
      "file": "framer-motion.js",
      "fileHash": "49ccc9bd",
      "needsInterop": false
    },
    "react-icons/fa": {
      "src": "../../node_modules/react-icons/fa/index.mjs",
      "file": "react-icons_fa.js",
      "fileHash": "4d573b02",
      "needsInterop": false
    },
    "gsap": {
      "src": "../../node_modules/gsap/index.js",
      "file": "gsap.js",
      "fileHash": "88f5c05b",
      "needsInterop": false
    },
    "@react-spring/web": {
      "src": "../../node_modules/@react-spring/web/dist/react-spring_web.modern.mjs",
      "file": "@react-spring_web.js",
      "fileHash": "76f4fe92",
      "needsInterop": false
    },
    "gsap/ScrollTrigger": {
      "src": "../../node_modules/gsap/ScrollTrigger.js",
      "file": "gsap_ScrollTrigger.js",
      "fileHash": "a97d69db",
      "needsInterop": false
    },
    "clsx": {
      "src": "../../node_modules/clsx/dist/clsx.mjs",
      "file": "clsx.js",
      "fileHash": "52edf6f5",
      "needsInterop": false
    },
    "tailwind-merge": {
      "src": "../../node_modules/tailwind-merge/dist/bundle-mjs.mjs",
      "file": "tailwind-merge.js",
      "fileHash": "74188c89",
      "needsInterop": false
    }
  },
  "chunks": {
    "chunk-IFXVA7FZ": {
      "file": "chunk-IFXVA7FZ.js"
    },
    "chunk-TKHB4QMX": {
      "file": "chunk-TKHB4QMX.js"
    },
    "chunk-YLDSBLSF": {
      "file": "chunk-YLDSBLSF.js"
    },
    "chunk-DC5AMYBS": {
      "file": "chunk-DC5AMYBS.js"
    }
  }
}